setup.py
dsnd_probability_practice/Binomialdistribution.py
dsnd_probability_practice/Gaussiandistribution.py
dsnd_probability_practice/Generaldistribution.py
dsnd_probability_practice/__init__.py
dsnd_probability_practice.egg-info/PKG-INFO
dsnd_probability_practice.egg-info/SOURCES.txt
dsnd_probability_practice.egg-info/dependency_links.txt
dsnd_probability_practice.egg-info/not-zip-safe
dsnd_probability_practice.egg-info/top_level.txt