Metadata-Version: 1.0
Name: dsnd-probability-practice
Version: 1.1
Summary: Gaussian and Binomial distributions
Home-page: UNKNOWN
Author: Jambal Tumurtogoo
Author-email: tjambal21@gmail.com
License: UNKNOWN
Platform: UNKNOWN
